metalearn/__init__.py
quantum_metalearn-1.1.2.dist-info/LICENSE
quantum_metalearn-1.1.2.dist-info/METADATA
quantum_metalearn-1.1.2.dist-info/WHEEL
quantum_metalearn-1.1.2.dist-info/entry_points.txt
quantum_metalearn-1.1.2.dist-info/top_level.txt
quantum_metalearn-1.1.2.dist-info/RECORD
