Metadata-Version: 2.2
Name: quantum-metalearn
Version: 1.1.2
Summary: A project for meta-learning experiments
Author: Krishna Bajpai
Author-email: bajpaikrishna715@gmail.com
License: MIT
Classifier: Programming Language :: Python :: 3
Classifier: Programming Language :: Python :: 3.9
Classifier: Programming Language :: Python :: 3.10
Classifier: Programming Language :: Python :: 3.11
Classifier: License :: OSI Approved :: MIT License
Classifier: Operating System :: OS Independent
Requires-Python: >=3.9
License-File: LICENSE
Requires-Dist: torch>=2.0.0
Requires-Dist: gymnasium>=0.28.0
Requires-Dist: numpy>=1.23.0
Requires-Dist: tqdm>=4.65.0
Requires-Dist: click>=8.1.0
Dynamic: author
Dynamic: author-email
Dynamic: classifier
Dynamic: description
Dynamic: description-content-type
Dynamic: license
Dynamic: requires-dist
Dynamic: requires-python
Dynamic: summary
